tarik_rsa/__init__.py
tarik_rsa/functions.py
tarik_cryptography_rsa-0.1.dist-info/METADATA
tarik_cryptography_rsa-0.1.dist-info/WHEEL
tarik_cryptography_rsa-0.1.dist-info/top_level.txt
tarik_cryptography_rsa-0.1.dist-info/RECORD
