Metadata-Version: 2.1
Name: tarik-cryptography-rsa
Version: 0.1
Requires-Dist: cryptography
